json2xml2csv/json_to_xml_utils.py
json2xml2csv/__init__.py
json2xml2csv/json_to_xml.py
json2xml2csv/args.py
json2xml2csv-1.0.0.dev1.dist-info/RECORD
json2xml2csv-1.0.0.dev1.dist-info/entry_points.txt
json2xml2csv-1.0.0.dev1.dist-info/WHEEL
json2xml2csv-1.0.0.dev1.dist-info/METADATA
json2xml2csv-1.0.0.dev1.dist-info/DESCRIPTION.rst
json2xml2csv-1.0.0.dev1.dist-info/top_level.txt
json2xml2csv-1.0.0.dev1.dist-info/metadata.json
